{
  "业务总览": "nav.groups.overview",
  "客户管理": "nav.groups.resources",
  "专线业务": "nav.groups.circuits",
  "网络与控制面": "nav.groups.network",
  "可观测性": "nav.groups.ops",
  "平台治理": "nav.groups.system",
  "运营驾驶舱": "page.dashboard",
  "客户": "page.tenants",
  "Fabric 站点": "page.sites",
  "网络设备": "page.devices",
  "专线管理": "page.circuits",
  "操作日志": "page.workOrders",
  "SDN 控制器": "page.controllers",
  "控制面视图": "page.controlPlane",
  "配置中心": "page.config",
  "物理拓扑": "page.topology",
  "容量规划": "page.capacity",
  "流量洞察": "page.monitoring",
  "告警态势": "page.alarms",
  "平台设置": "settings.title",
  "保存": "action.save",
  "取消": "action.cancel",
  "退出登录": "action.logout",
  "修改密码": "action.changePassword",
  "个人设置": "account.title",
  "创建": "action.create",
  "开通专线": "action.createCircuit",
  "编辑": "action.edit",
  "删除": "action.delete",
  "导出": "action.export",
  "导入": "action.import",
  "刷新": "action.refresh",
  "进入平台": "action.login",
  "确认": "action.confirm",
  "全域视图": "action.viewAll",
  "立即学习": "action.learnNow",
  "确认告警": "action.ack",
  "账号资料": "account.profile",
  "语言与时区": "account.preferences",
  "账号": "account.username",
  "角色": "account.role",
  "姓名 / 称呼": "account.fullName",
  "请输入姓名": "account.fullNamePlaceholder",
  "邮箱": "account.email",
  "name@example.com": "account.emailPlaceholder",
  "用于接收登录验证码、密码找回邮件": "account.emailTooltip",
  "保存资料": "account.saveProfile",
  "资料已更新": "account.profileSaved",
  "保存失败": "account.saveFailed",
  "界面语言": "account.language",
  "时区": "account.timezone",
  "图表、告警与审计时间将按此时区显示": "account.timezoneHint",
  "偏好已保存": "account.preferencesSaved",
  "简体中文": "account.languageZh",
  "English": "account.languageEn",
  "总览": "portal.menu.dashboard",
  "我的专线": "portal.menu.circuits",
  "账号与安全": "portal.menu.account",
  "租户管理员": "portal.roleTenantAdmin",
  "租户只读": "portal.roleTenantViewer",
  "客户门户": "portal.portalLabel",
  "客户自助门户": "portal.selfService",
  "专线自助服务": "portal.circuitService",
  "加载中…": "common.loading",
  "近 1 小时": "monitor.last1h",
  "近 6 小时": "monitor.last6h",
  "近 24 小时": "monitor.last24h",
  "近 7 天": "monitor.last7d",
  "近 30 天": "monitor.last30d",
  "近 {{hours}} 小时": "monitor.lastNh",
  "Bugis Network": "brand.loginTitle",
  "DCI · EVPN 全域智能运营": "brand.tagline",
  "DCI / EVPN 全域网络运营中枢": "brand.header",
  "Multi-Vendor · BGP EVPN · Intelligent Fabric Ops": "brand.loginSubtitle",
  "DCI / EVPN 运营驾驶舱": "brand.heroTitle",
  "多厂商异构 · VXLAN / SR-MPLS EVPN · 自研 SDN · 跨域 DCI": "brand.heroSubtitle",
  "暂无记录": "empty.default",
  "暂无专线 · 点击右上角创建首条 Circuit": "empty.circuits",
  "暂无设备 · 从导入或纳管开始": "empty.devices",
  "尚无配置快照 · 可先备份或执行现网学习": "empty.snapshots",
  "流量数据采集中 · 巡检引擎即将写入时序": "empty.traffic",
  "全网健康 · 零活跃告警": "empty.alarms",
  "数据加载后将在此呈现": "empty.data",
  "← 选择左侧设备以查看配置": "empty.selectDevice",
  "尚未同步现网配置 · 一键拉取 Running Config": "empty.noLearn",
  "已保存": "toast.saved",
  "已删除": "toast.deleted",
  "创建成功": "toast.created",
  "操作失败，请重试": "toast.failed",
  "欢迎回来": "toast.loginOk",
  "凭证无效，请检查后重试": "toast.loginFail",
  "专线管理 · Circuit Studio": "page.circuitsFull",
  "操作审计": "settings.nav.audit",
  "用户权限": "settings.nav.users",
  "通知渠道": "settings.nav.notifications",
  "北向集成": "settings.nav.integration",
  "草稿": "status.workOrder.draft",
  "待开通": "status.circuit.pending",
  "开通中": "status.circuit.provisioning",
  "运行中": "status.circuit.active",
  "降级": "status.circuit.degraded",
  "已暂停": "status.tenant.suspended",
  "已退服": "status.circuit.decommissioned",
  "失败": "status.workOrder.failed",
  "已提交": "status.workOrder.submitted",
  "已审批": "status.workOrder.approved",
  "已驳回": "status.workOrder.rejected",
  "已排期": "status.workOrder.scheduled",
  "执行中": "status.workOrder.running",
  "已完成": "status.workOrder.completed",
  "已取消": "status.workOrder.cancelled",
  "正常": "status.tenant.active",
  "已终止": "status.tenant.terminated",
  "隧道异常": "status.alarmKind.tunnel_down",
  "业务中断": "status.alarmKind.circuit_interruption",
  "丢包超标": "status.alarmKind.sla_loss",
  "时延超标": "status.alarmKind.sla_latency",
  "带宽拥塞": "status.alarmKind.utilization",
  "健康劣化": "status.alarmKind.health",
  "闪断频繁": "status.alarmKind.circuit_flap",
  "骨干拥塞": "status.alarmKind.link_utilization",
  "测试通知": "status.alarmKind.test",
  "紧急 P1": "status.alarmSeverity.critical",
  "重要 P2": "status.alarmSeverity.major",
  "一般 P3": "status.alarmSeverity.minor",
  "提示": "status.alarmSeverity.warning",
  "信息": "status.alarmSeverity.info",
  "活跃": "status.alarm.active",
  "已确认": "status.alarm.acknowledged",
  "已恢复": "status.alarm.cleared",
  "二层 EVPN": "status.serviceType.l2vpn_evpn",
  "三层 EVPN": "status.serviceType.l3vpn_evpn",
  "Remote IPT": "status.serviceType.remote_ipt",
  "EVPN VPWS": "status.serviceType.evpn_vpws",
  "DCI 互联": "status.serviceType.dci",
  "在线": "status.port.up",
  "离线": "status.port.down",
  "维护": "status.device.maintenance",
  "未知": "status.port.unknown",
  "无标签": "status.accessMode.access",
  "单标签": "status.accessMode.dot1q",
  "双标签": "status.accessMode.qinq",
  "SNMP": "status.discoveredVia.snmp",
  "SNMP 模拟": "status.discoveredVia.snmp-sim",
  "运行配置": "status.discoveredVia.running-config",
  "H3C 新华三": "form.vendor.h3c",
  "Huawei 华为": "form.vendor.huawei",
  "Juniper 瞻博": "form.vendor.juniper",
  "Arista": "form.vendor.arista",
  "Cisco 思科": "form.vendor.cisco",
  "FRR 开源路由": "form.vendor.frr",
  "Spine 核心": "form.deviceRole.spine",
  "Leaf 接入": "form.deviceRole.leaf",
  "Border Leaf 边界": "form.deviceRole.border_leaf",
  "VTEP 隧道端点": "form.deviceRole.vtep",
  "PE 提供商边缘": "form.deviceRole.pe",
  "P 核心路由器": "form.deviceRole.p",
  "RR 路由反射器": "form.deviceRole.rr",
  "DCI Gateway 互联网关": "form.deviceRole.dci_gw",
  "CPE 客户设备": "form.deviceRole.cpe",
  "自动（按厂商默认）": "form.managementTransport.auto",
  "NETCONF": "form.managementTransport.netconf",
  "SSH CLI": "form.managementTransport.ssh",
  "暂无数据": "table.noData",
  "第 {{start}}–{{end}} 条，共 {{total}} 条": "table.range",
  "共 {{total}} 条": "table.totalOnly",
  "千兆": "network.gigabit",
  "接口全名：{{name}}": "network.fullName",
  "集中管理品牌外观、平台运行参数、告警策略、SNMP/邮件、北向集成与用户权限。修改后即时生效。": "settings.intro",
  "品牌外观": "settings.nav.brand",
  "平台运行": "settings.nav.general",
  "配置管理": "settings.nav.configLearn",
  "告警阈值": "settings.nav.alarms",
  "设备基线": "settings.nav.baseline",
  "邮件 SMTP": "settings.nav.smtp",
  "南向接口": "settings.nav.management",
  "SNMP 采集": "settings.nav.snmp",
  "安全认证": "settings.nav.security",
  "—": "common.dash",
  "开": "common.on",
  "关": "common.off",
  "可选": "common.optional",
  " : \"\"} (${data.latency_ms}ms) · 已扫描 ${svidCount} 个 S-VID 占用${activeTag}${dryTag}": "auto.d86d7c0e",
  " : \"\"} · 请检查 IP、端口、SNMP Community 与防火墙": "auto.7d74c320",
  " · ${topo.nodes.length} 台设备 · ${scopedVnis.length} 个 VNI · 选择 VNI 查看隧道": "auto.c267aad5",
  " · 已清理 ${cleaned} 条陈旧拓扑": "auto.c465b3b3",
  " · 当前 ${data.mgmt_ip_active_label || data.mgmt_ip_active_role} ${data.mgmt_ip_active}": "auto.d9772fab",
  " · 当前 VNI ${selectedVni} · ${selectedRow?.deviceCount ?? 0} 台设备 · ${tunnelCount} 条隧道": "auto.bfbd11e5",
  " · 现网学习 ${data.learn.success}/${data.learn.total} 成功": "auto.7da5c47a",
  " · 筛选后 ${ifaceRows.length}": "auto.1eac7adc",
  " · 设备 ${selectedDevice.name} · ${deviceVnis.length} 个 VNI": "auto.ee6ea1c0",
  " · 配置 dry-run": "auto.bda2af9d",
  "${action.confirm}${action.delete}该工单？": "auto.9a7adcc1",
  "${c.name} (内置 · 推荐)": "auto.d1b0c81e",
  "${d.name} (站点 ${d.site_id})": "auto.bdfc4123",
  "${d.name} 学习完成 · ${inv?.service_count ?? 0} 个业务 · v${data.snapshot_version}": "auto.57e6d810",
  "${data.device} 初始化完成 · v${data.version} · ${data.transport}": "auto.3da533a6",
  "${data.device} 可达 · 发现 ${svidCount} 个 S-VID · ${conflictCount} 处冲突": "auto.49bcb41c",
  "${data.device} 可达${data.method ? ": "auto.3d7069c9",
  "${data.device} 管理面不可达${data.mgmt_ip_backup ? ": "auto.def62ea6",
  "${data.errors.length} 行需修正": "auto.eb1a9875",
  "${exportable.length} 个工单可导出": "auto.556d10a8",
  "${me.tenant_name} · 专线自助服务": "auto.8f79f8a2",
  "${n} 条/页": "auto.7b2e1dfc",
  "${result.config_jobs.filter((j) => j.status === \"succeeded\" || j.status === \"dry_run\").length} / ${result.config_jobs.length} 个设备作业成功": "auto.a6de63ee",
  "${vniText}<br/>状态 ${up ? \"Up\" : node.status}": "auto.2edebb0d",
  "${v} 台": "auto.cc633913",
  "${windowLabel} 发生 ${availability.flash_count} 次闪断": "auto.95b36365",
  "${windowLabel} 发生 ${availability.interruption_count} 次中断，累计 ${Math.round(availability.total_downtime_sec / 60)} 分钟": "auto.d91a34df",
  "(空)": "auto.756aadc2",
  "10.1.0.11 或内网地址": "auto.9ab78e51",
  "126 邮箱地址": "auto.b1e69d4f",
  "15 分钟内闪断 ${availability.flap_count} 次，请关注链路稳定性": "auto.47f8706e",
  "163 邮箱地址": "auto.47452535",
  "5 分钟粒度采样 · 95 计费 · 历史数据永久保留": "auto.f8e377fe",
  "6 位数字": "auto.a87595f9",
  "6 位验证码": "auto.b7a51032",
  "95 计费说明": "auto.e22fda0e",
  "<b>${n.name}</b><br/>厂商 ${n.vendor.toUpperCase()} · ${roleLabel(n.role)}<br/>": "auto.1bc32fa6",
  "<b>${p.name}</b><br/>${p.value} 台": "auto.d12c3e1a",
  "<b>${p.name}</b><br/>${p.value} 条 · ${pct}%": "auto.28e8b21f",
  "<b>${p.name}</b><br/>峰值利用率 <b>${p.value}%</b>": "auto.b95caaa0",
  "<div style=\"font-weight:600;margin-bottom:6px\">采样 #${list[0]?.name ?? \"\"}</div>${rows}": "auto.5ab9f909",
  "A 端": "auto.f5c78954",
  "A 端端口${candidatesA.length ? ": "auto.d5503f85",
  "A 端设备": "auto.27e55cb8",
  "AWS SES 控制台创建 SMTP 凭证；发件人需在 SES 验证。": "auto.b8c28925",
  "Access · 不带标签": "auto.b1eda940",
  "Admin 管理员": "auto.495376db",
  "Ansible 编排导出": "auto.27d3c400",
  "Ansible 预览": "auto.ee1c2ea8",
  "Ansible 预览 · ${preview.code}": "auto.f2208642",
  "BGP EVPN + OSPF 底层": "auto.f3542b97",
  "BGP EVPN 对等会话": "auto.8bf4522b",
  "BGP 会话": "auto.506ce14a",
  "BGP 会话在线": "auto.2e846c82",
  "BGP 会话已同步": "auto.3719daa9",
  "Bugis SDN 控制器": "auto.146f2eed",
  "Bugis SDN 控制器 (内置)": "auto.246d99a7",
  "C:自动": "auto.a01c6ed0",
  "CSS background 值，如 linear-gradient(...) 或 #2b1402": "auto.98f5affb",
  "CSV 导入或手动新增设备时立即执行一次现网学习": "auto.497fdd83",
  "Critical 严重": "auto.95c4e1c7",
  "DCI 专线全生命周期管理": "auto.78ab7780",
  "Dot1Q · 单标签": "auto.2f3f74b4",
  "Dry-run 模式（模拟下发）": "auto.ecf09ccb",
  "Dry-run 模式：配置不下发至设备，拨测为模拟结果": "auto.5706d522",
  "Dry-run（模拟下发）": "auto.07f60ac4",
  "EVPN VXLAN 智能编排": "auto.99e1cd71",
  "EVPN 标识（VNI / VSI · 留空自动编排）": "auto.d6c5636c",
  "EVPN 路由": "auto.8c1d0476",
  "EVPN 路由条目": "auto.eb096f94",
  "EVPN 路由表 (RIB)": "auto.340fdadf",
  "Enable 密码": "auto.6682f787",
  "Fabric 内链路": "auto.c2154b15",
  "Fabric 容量 · 站点分配": "auto.8f44cbdc",
  "Fabric 总容量": "auto.8ccb93a6",
  "Fabric 站点容量（${sites.length}）": "auto.c90c31fb",
  "Fabric 逐跳 Ping": "auto.a87b3030",
  "Fastmail 账号": "auto.e3e9b11c",
  "Foxmail 邮箱地址": "auto.9497e005",
  "Gmail 地址": "auto.f3957519",
  "H3C 等设备 VSI 实例名，留空则按编码自动生成": "auto.2c321e7f",
  "IGP 自动": "auto.0b93e0df",
  "IOS-XR NETCONF 830；账号常为 admin / cisco": "auto.285ef5b7",
  "Info 信息": "auto.3fd8fa90",
  "MFA 已关闭": "auto.b36f4d6f",
  "MFA 状态": "auto.3688b27b",
  "MPLS 标签": "auto.2a016519",
  "Mailgun 控制台 → Sending → SMTP credentials。": "auto.bb7b0694",
  "Major 重要": "auto.60d0004b",
  "Microsoft 365 邮箱": "auto.df55ff5a",
  "Minor 次要": "auto.28464218",
  "NETCONF 端口": "auto.c39ee3d6",
  "NETCONF 超时 (秒)": "auto.fa7bc3bf",
  "NTP 服务器": "auto.271db6e6",
  "Netmiko 设备类型": "auto.c9472a45",
  "Operator 操作员": "auto.554e89f8",
  "Outlook 邮箱地址": "auto.cc6ee532",
  "Overlay 尚未建立 · 开通控制器托管专线后自动呈现": "auto.ff775a06",
  "Overlay 技术": "auto.068272cb",
  "Prometheus 指标": "auto.c387a108",
  "Proton Bridge 本地账号": "auto.31d13584",
  "QQ 邮箱": "auto.d959ef7c",
  "QinQ S:${vlanId}/C:${innerVlanId} 已被占用": "auto.3b1010c1",
  "QinQ · 双标签": "auto.c354a1a9",
  "RIB 为空 · 等待路由同步": "auto.846bfa45",
  "RIB 版本": "auto.0020bc46",
  "S-VID ${vlanId} 已被占用": "auto.0a34a34c",
  "S-VID 冲突": "auto.3d6be035",
  "S-VID 占用": "auto.9c90e465",
  "S-VID 占用 · ${count.toLocaleString()} 个": "auto.cd24c261",
  "S-VID 需从 running-config 解析，请执行「现网学习」后重新检测": "auto.10bcf9fe",
  "S:自动": "auto.5aaaa5c3",
  "SDN 控制面 · Bugis Controller": "auto.72830508",
  "SLA 告警阈值（可选 · 留空继承平台默认）": "auto.ab76d835",
  "SMTP 主机": "auto.599417fe",
  "SMTP 参数已保存": "auto.e02b09ac",
  "SMTP 密钥在 Brevo → SMTP & API 获取。": "auto.f1eea3db",
  "SMTP 用户名": "auto.e2df5728",
  "SMTP 用户名 (IAM)": "auto.c760d203",
  "SMTP 登录账号": "auto.ddede005",
  "SNMP community 请在「SNMP 采集」页配置 baseline_community。": "auto.a3098ebb",
  "SNMP 不可达，已从 running-config 解析 ${data.length} 个物理口（${svidCount} 个有 S-VID 占用）": "auto.177c1f59",
  "SNMP 参数已保存": "auto.e698d585",
  "SNMP 发现": "auto.64b6eac6",
  "SNMP 发现 ${data.length} 个接口 · ${svidCount} 个端口有 S-VID 占用": "auto.3bf4c2b4",
  "SNMP 发现 + S-VID 扫描...": "auto.b1384910",
  "SNMP 发现失败": "auto.2875e374",
  "SNMP 接口发现失败": "auto.cba0e478",
  "SNMP 接口扫描中…": "auto.bc10e814",
  "SNMP 接口扫描中…（主备管理 IP 自动探测）": "auto.2b72a6f1",
  "SNMP 未启用：流量/链路负载需配置 SNMP 后才有实测数据": "auto.25f50272",
  "SNMP 未采集到 IF-MIB，已从现网配置/SSH 拉取的 running-config 提取物理接口名。如需速率/状态，请确保管理网 SNMP 16161 可达。": "auto.8bbb01ff",
  "SNMP 流量与可用性数据在专线激活（active）后通过 SNMP 与拨测采集；草稿/失败状态仅展示历史数据。": "auto.5729b38d",
  "SNMP 版本": "auto.c17b2e99",
  "SNMP 设置加载失败": "auto.a97982fa",
  "SNMP 设置接口未部署，请确认后端已升级并执行数据库迁移": "auto.67642293",
  "SNMP 连通性测试": "auto.011b0dac",
  "SNMP 采集 ${data.collected} 条${data.skipped ? ": "auto.d0a356d0",
  "SNMPv3 用户名": "auto.d0fe707a",
  "SR 显式": "auto.d9c11ecf",
  "SR 节点": "auto.3bfa7fb0",
  "SR-MPLS 支持显式路径": "auto.a7460b70",
  "SSH 22，vtysh CLI；账号为 Linux 用户": "auto.ec43a7f0",
  "SSH 端口": "auto.3f284a59",
  "SSH 超时 (秒)": "auto.2e437e57",
  "SSL/TLS (端口 465)": "auto.6db2126f",
  "STARTTLS (推荐，端口 587)": "auto.2fbe1c2c",
  "Service VLAN，留空则自动分配": "auto.c0afeda0",
  "Site Key (公开)": "auto.8a0719f9",
  "Syslog 服务器": "auto.d1dccbd9",
  "Turnstile 脚本加载失败": "auto.837f3da8",
  "Type-5 IP前缀": "auto.05afa3f3",
  "Type-5 前缀": "auto.0762388d",
  "UDP 端口": "auto.4735c78f",
  "URL 或上传图片": "auto.e20bd067",
  "Underlay 可达": "auto.b02aa6a4",
  "Underlay 异常": "auto.567c6c52",
  "Underlay 网段": "auto.28f11fc4",
  "VLAN / 端口占用校验": "auto.470ac2da",
  "VLAN 数": "auto.c75d6fcf",
  "VNI ${row.vni} · ${row.deviceCount} 台${row.platformManaged ? \" · 平台\" : \"\"}": "auto.adc27369",
  "VNI 范围 1–16777215": "auto.4059a53b",
  "VSI / 服务": "auto.93a9f95e",
  "VSI 名称": "auto.f27ca80b",
  "VTEP 节点": "auto.3e06e5d7",
  "VTEP 邻居表": "auto.9158f4b7",
  "VXLAN 专线无法指定经由设备，流量按 OSPF/IGP 最短路径自动转发。": "auto.b8a59061",
  "Viewer 只读": "auto.8f8cc9db",
  "Warning 警告": "auto.8c4ce044",
  "Webhook Token 已保存": "auto.d384131d",
  "Webhook 地址": "auto.80a0d371",
  "Yahoo 邮箱": "auto.f886a224",
  "Yeah.net 邮箱地址": "auto.1bfd25dc",
  "Z 端": "auto.3cd8f630",
  "Z 端端口${candidatesZ.length ? ": "auto.c9c8fd79",
  "Z 端设备": "auto.52e29dd5",
  "Zoho Mail (企业)": "auto.28a5a293",
  "Zoho 企业邮箱": "auto.48ee88e5",
  "Zoho 邮箱": "auto.bfad3d01",
  "iCloud 邮箱": "auto.188ffdf1",
  "snmp-sim 表示未从设备读到真实 IF-MIB。请确认 SNMP Community 与 UDP 161 可达后重新发现。": "auto.fe876c41",
  "一键开通 (下发配置)": "auto.4f02b111",
  "上联": "auto.2de4ea3b",
  "上行": "auto.e18c94a2",
  "下一跳": "auto.ae53795a",
  "下发中…": "auto.37c56a71",
  "下发前用缓存的现网学习快照刷新接口 S-VID 占用，让冲突预检基于最新现网状态": "auto.291b0eea",
  "下发基线配置": "auto.b069587e",
  "下发失败": "auto.c4a86b60",
  "下发模式": "auto.765633cd",
  "下载失败": "auto.65e200d3",
  "不可达": "auto.834f7cd8",
  "与 QQ 邮箱共用 SMTP，使用授权码登录。": "auto.92775fe9",
  "与 QQ 邮箱相同": "auto.cc230749",
  "与 SNMP/拨测调度独立计时，建议 60–300 秒": "auto.5bf87215",
  "专线": "auto.175d02d5",
  "专线 ${c.code} 已删除": "auto.5e9f3a72",
  "专线 ${current.code} 当前状态为「${STATUS_LABEL[current.status] || current.status}」": "auto.621061e2",
  "专线 ${u.circuit_code}": "auto.5d2e36cc",
  "专线 ID": "auto.232429bd",
  "专线列表加载失败": "auto.f303fc1c",
  "专线列表加载失败，请刷新重试": "auto.06d0c24c",
  "专线名称": "auto.dd178342",
  "专线已创建（草稿），可点击开通下发配置": "auto.014ad8d7",
  "专线总数": "auto.f9a2f536",
  "专线数": "auto.49ae9deb",
  "专线激活后可查看 SNMP 流量、95 值、时延与中断记录": "auto.408884a7",
  "专线状态：${CIRCUIT_STATUS_LABEL[result.circuit_status] || result.circuit_status}": "auto.2153774c",
  "专线生命周期 · 状态分布": "auto.b763f6a7",
  "业务": "auto.4af9dc31",
  "业务名称": "auto.fcbd12b3",
  "业务数": "auto.1b7f2341",
  "业务类型": "auto.09ab4243",
  "丢包": "auto.4d3b62ff",
  "丢包 (%)": "auto.c7535aea",
  "丢包告警 (%)": "auto.abe7b219",
  "丢包率阈值 (%)": "auto.2298ab2f",
  "两次输入不一致": "auto.6a6dfeb1",
  "两次输入的密码不一致": "auto.6046d642",
  "中国 (上海)": "auto.faf6105f",
  "中国 CN": "auto.fdf37f7c",
  "中国台湾 (台北)": "auto.9db2d617",
  "中国香港": "auto.0242e5f1",
  "中断": "auto.d8d7ca77",
  "中断 / 闪断事件": "auto.2a3f99aa",
  "中欧 (巴黎)": "auto.d8565b50",
  "临时 Community": "auto.c159651f",
  "主": "auto.7bbc7364",
  "主 IP 类型": "auto.f434d4d1",
  "主 Logo（侧栏 / 登录）": "auto.5c322104",
  "主机": "auto.65227369",
  "主管理 IP": "auto.3f847db5",
  "事务邮件 ESP": "auto.25ea2330",
  "云邮件服务": "auto.c0433f1c",
  "产品 Tagline": "auto.d304c6cf",
  "产品名称（侧栏）": "auto.e5e4ecb1",
  "人机验证组件加载失败": "auto.636195c6",
  "仅 Admin 角色可管理用户与权限": "auto.e7cf90dd",
  "仅 down": "auto.bf2490fe",
  "仅 up": "auto.b886c18e",
  "仅允许字母、数字、下划线、连字符": "auto.0e5e7e8c",
  "仅删除系统记录，设备配置应已通过拆除工单清除": "auto.406fd1d4",
  "仅包含 (正则)": "auto.23e606eb",
  "仅展示贵司租户下的专线资源": "auto.30e5b359",
  "仅有占用": "auto.49ba5821",
  "今天": "auto.800dfdd9",
  "从现网选择额外接入节点并登记到平台，不会向设备下发任何配置。新增端点须为设备上已存在的 S-VID 绑定，且 VNI/VSI 须与本专线一致。": "auto.fce28946",
  "从端口描述 bw(100Mbps) 同步链路合同带宽": "auto.86119273",
  "以下选项影响开通/拆除前的现网快照与下发前冲突预检，建议保持开启。": "auto.cbf48334",
  "任意用户名": "auto.bd64eb79",
  "企业专线": "auto.ea30c4fb",
  "企业微信": "auto.ff17b9f9",
  "企业版可用 smtppro.zoho.com。": "auto.4ec0d0ec",
  "企业邮箱账号": "auto.375935fb",
  "优先使用设备凭证": "auto.65cbd435",
  "传输": "auto.bc282335",
  "传输方式": "auto.8da128d0",
  "作用于全平台 SNMP 发现": "auto.20ae283a",
  "使用默认值（生产环境请修改）": "auto.0e3155db",
  "例如 10.1.0.0/16": "auto.6c96b6d6",
  "例如 65001": "auto.be26d257",
  "例如 BANK-BJ": "auto.472d2fca",
  "例如 BJ-DC1": "auto.dc7403ff",
  "例如 NOC 运维群": "auto.4f020333",
  "例如 US": "auto.163498cf",
  "例如 acme_ops": "auto.f09e57c2",
  "例如 vsi_cir_ab12cd": "auto.753a88ec",
  "例如 北京 Fabric PoP": "auto.2ddaf461",
  "例如 华为 iMaster NCE-Fabric": "auto.81537137",
  "例如 华北": "auto.b0f1feca",
  "例如 银行北京-上海二层专线": "auto.8b28650e",
  "依据": "auto.fcf69835",
  "依赖 / 资源占用确认": "auto.f59efcb7",
  "保存修改": "auto.c5575b3f",
  "保存并开通": "auto.f9b48f0b",
  "保存并重新下发": "auto.ebd9b23f",
  "保存接口描述失败": "auto.0219b007",
  "保存（不下发）": "auto.ed08333b",
  "保留 VNI": "auto.0985a3a1",
  "修改后将同步应用于登录页、侧栏 Logo、顶栏标题与运营驾驶舱横幅。Logo 支持 PNG / SVG / WebP（Base64 存储，建议小于 512KB）。": "auto.352e4446",
  "修改失败": "auto.5badb3ba",
  "修改接入端点": "auto.e5fda04c",
  "修改端点": "auto.0b26bcc9",
  "修改端点 · ${editEndpointsTarget.code}": "auto.6130c5f8",
  "修改端点并重新下发": "auto.216d1d04",
  "修改设备基础信息、南向凭证与 SNMP 配置。密码类字段留空则保持原值。": "auto.df667a74",
  "停用": "auto.5c56a889",
  "健康分下限": "auto.7900e41c",
  "健康指数": "auto.f11eb4b0",
  "允许邮件 OTP": "auto.a71821e6",
  "允许验证器": "auto.c304fa11",
  "入向 95": "auto.38a3aebe",
  "全域": "auto.7fc087f1",
  "全网流量态势 · Rx/Tx 聚合 (Mbps)": "auto.ad3f8679",
  "全部 (${vniIndex.length})": "auto.0cb185b3",
  "全部客户 (${overview.tenants_total.toLocaleString()})": "auto.a6b623f6",
  "全部状态": "auto.443483c9",
  "公有云接入": "auto.f071c9fd",
  "公网": "auto.2c2dc240",
  "公网 IP": "auto.a1d4e623",
  "公网 IP（可选）": "auto.f95f46ea",
  "公网出口国家/地区": "auto.c058a03d",
  "共 ${rows.length} 条": "auto.cd74a8c7",
  "共 ${t.toLocaleString()} 条": "auto.a9980e8f",
  "共 ${total.toLocaleString()} 台 · ${stats.online} 在线 · ${stats.offline} 离线": "auto.72661f75",
  "共 ${total} 个": "auto.7c00dadc",
  "共 ${total} 个版本": "auto.25425415",
  "共 ${total} 个端口": "auto.bbdcd84b",
  "共 ${total} 条关联": "auto.9a354ba3",
  "共 ${total} 项": "auto.209f45a3",
  "共 ${t} 个": "auto.0c339610",
  "共 ${t} 个站点": "auto.f755c350",
  "共 ${t} 张工单": "auto.1e07babd",
  "共 ${t} 条": "auto.292440ea",
  "关联控制器": "auto.23dc1779",
  "关闭": "auto.b15d9127",
  "关闭后不对该专线进行路径拨测，监控页不展示时延/抖动/丢包": "auto.5490b5f0",
  "关闭失败": "auto.1fb27526",
  "其他": "auto.0d98c747",
  "内层 VLAN": "auto.0e493ea1",
  "内置 Bugis SDN 控制器 · 无需手动纳管": "auto.e8420197",
  "内置 vs 北向控制器": "auto.f1c6e98e",
  "内置控制器": "auto.6e09912b",
  "内置控制器不可移除": "auto.46eef43e",
  "内部业务": "auto.b9e9d8e8",
  "凭证": "auto.94171ce2",
  "出口 NAT": "auto.e9f5e7cd",
  "出口 PoP 站点": "auto.0e07a513",
  "出口国家": "auto.948945be",
  "出口站点": "auto.fc99230b",
  "出向 95": "auto.41a7da23",
  "创建失败": "auto.a889286a",
  "创建时间": "auto.eca37cb0",
  "创建此链路": "auto.df8fbba2",
  "初始化": "auto.2cb472ff",
  "初始化失败": "auto.ab94e2c3",
  "初始化模板 Community": "auto.57937959",
  "初始密码": "auto.763ffee1",
  "删除失败": "auto.acf0664a",
  "删除用户": "auto.10991ce4",
  "删除该骨干链路？": "auto.0c6ab9ee",
  "删除骨干链路失败": "auto.6772bdb2",
  "利用率": "auto.bbdff9f6",
  "利用率告警阈值 (%)": "auto.191a20f3",
  "加密密码": "auto.24cf63e2",
  "加密方式": "auto.75409f09",
  "加密算法": "auto.8f62705b",
  "加载 SNMP 设置失败": "auto.b3b90f6f",
  "加载控制器数据失败": "auto.4b190661",
  "加载配置历史失败": "auto.93d2ee26",
  "加载配置差异失败": "auto.1bd79afe",
  "加载集成数据失败": "auto.6f76efba",
  "北向 Webhook 接入 (StackStorm / ITSM)": "auto.4f54fb45",
  "北向地址": "auto.57437606",
  "北向控制器": "auto.ed3fbbeb",
  "区域": "auto.d3ce40d8",
  "华三 / 华为 / 思科 / Juniper": "auto.d9ec10af",
  "华三 SeerEngine": "auto.64d6614f",
  "华为": "auto.d63e7ea0",
  "华为 CE 常见 16161（非标准 161）": "auto.bf40ea54",
  "华为 NCE-Fabric": "auto.db455d2f",
  "华为云邮件": "auto.b46c4ce1",
  "华为云邮件账号": "auto.10b8b7dc",
  "单标签 Dot1Q": "auto.dda9ff5e",
  "南向接口默认参数已保存": "auto.cbeebb86",
  "南向驱动目录": "auto.f19c40fa",
  "厂商": "auto.70aefc6a",
  "参数详情": "auto.043456b7",
  "双因素认证已关闭": "auto.07256b56",
  "双因素认证已启用": "auto.b3cd9698",
  "双因素验证": "auto.3ac6e5bb",
  "双标签 QinQ": "auto.3f720eb6",
  "发件人地址": "auto.e180511c",
  "发现失败": "auto.06304f1e",
  "发路由": "auto.898e6bfa",
  "发送失败 · ${data.detail}": "auto.3a1012ab",
  "发送失败，请稍后再试": "auto.2faad269",
  "变更": "auto.1dd554cd",
  "变更保护与快照": "auto.226ac2d9",
  "变更前自动快照": "auto.fe4b97f6",
  "变更参数 / 告警": "auto.140e5f55",
  "变更参数 · ${modifyTarget?.code || \"\"}": "auto.cc1dfcc1",
  "变更失败": "auto.09e4961b",
  "变更工单 ${data.code}: ${data.status}": "auto.a3c3264e",
  "只读": "auto.85541bd9",
  "只读 Community": "auto.381d0dbc",
  "只读 — 查看专线与流量": "auto.ead6e301",
  "只读：当前账号无修改平台参数的权限": "auto.b20b42a8",
  "只读：当前账号无修改平台运行参数的权限": "auto.150637a4",
  "可指定经由的 P/PE 节点，控制器将下发 SR segment-list 策略。": "auto.99acf6b7",
  "可更换设备、物理端口、封装模式与 S-VID。保存后将先拆除变更前的旧接入配置，再下发新端点配置（创建变更/开通工单）。": "auto.a58eb6d4",
  "可用率": "auto.2b9b5369",
  "可达": "auto.e126a999",
  "可达性探测 · S-VID 扫描中…": "auto.43584635",
  "台": "auto.f923606a",
  "台湾 TW": "auto.f318ff36",
  "合同带宽": "auto.a2e883fa",
  "合同带宽 (Mbps)": "auto.53d0030f",
  "合规预检": "auto.9017414f",
  "同 IP 最大失败次数": "auto.a6d969fb",
  "同步合同带宽失败": "auto.00d6c8ee",
  "同步链路容量": "auto.f5122516",
  "名称": "auto.d7ec2d3f",
  "后台工作线程同时执行的设备下发数量上限。": "auto.1f2da29d",
  "后台按间隔对所有在线设备拉取 running-config，更新现网学习与 S-VID 占用": "auto.c37e9c26",
  "后台调度器": "auto.8901809f",
  "后台调度器已关闭": "auto.7eb2366a",
  "启用": "auto.7854b52a",
  "启用 SNMP 采集": "auto.b9ab3f48",
  "启用 Turnstile": "auto.b3bf491a",
  "告警": "auto.aa0eab9d",
  "告警参数已保存": "auto.5a60d3f6",
  "告警态势 · 按严重级别": "auto.b3419280",
  "告警阈值已保存": "auto.902193ba",
  "品牌与 Logo 自定义": "auto.45f5c3bc",
  "品牌与外观已保存": "auto.dc62289e",
  "回收作业完毕": "auto.ebda3a66",
  "回显": "auto.7a147777",
  "国内企业邮": "auto.c0c84ffe",
  "国内邮箱": "auto.b4fd02ab",
  "国际邮箱": "auto.a7c4e0a8",
  "图片请小于 512KB": "auto.a9bba479",
  "在线设备": "auto.6b02e98e",
  "在网专线": "auto.b878eab1",
  "在网专线 · 活跃/总量": "auto.a062e099",
  "在网带宽": "auto.3b9fac86",
  "在网带宽 (Mbps)": "auto.7ecafc2c",
  "型号": "auto.ac4190df",
  "基本": "auto.4092ed98",
  "基线初始化": "auto.d7b36090",
  "基线初始化 · ${initDevice.name} (${initDevice.vendor})": "auto.3afbf4e5",
  "填写设备基础信息与南向凭证，SNMP 与登录密码相互独立。": "auto.856c23b4",
  "备": "auto.bb93ed71",
  "备 IP 类型": "auto.7247bc55",
  "备份失败": "auto.6af91784",
  "备份完成 v${data.version} · ${data.lines} 行 · ${via}": "auto.7b408c75",
  "备注": "auto.2432b575",
  "备管理 IP": "auto.81f66b59",
  "复用学习 v${data.from_learned_version}": "auto.ad6ed08e",
  "外部控制器已纳管": "auto.90e62094",
  "多厂商 Fabric 纳管 · SNMP / NETCONF / SSH": "auto.765f5072",
  "多厂商统一纳管": "auto.7a7a3b39",
  "多数平台需使用授权码而非登录密码": "auto.456c3181",
  "失败 N 次后要求人机验证": "auto.d73d0cca",
  "姓名": "auto.60d0458a",
  "学习失败": "auto.6d6c099e",
  "学习时间": "auto.5898b79c",
  "学习版本": "auto.84f37ee9",
  "安全校验": "auto.dae4e63d",
  "安全策略已保存": "auto.aa781a09",
  "安全级别": "auto.de6691e6",
  "完整 QQ 邮箱地址": "auto.2307b729",
  "定时自动拉取": "auto.9c4a7532",
  "定时自动拉取已关闭": "auto.96c7fdaf",
  "定时自动拉取已开启（间隔 ${platform?.auto_learn_interval_seconds ?? 60} 秒）": "auto.eaaadae9",
  "实时预览": "auto.2f586bd4",
  "实测": "auto.e21d9457",
  "审批人": "auto.91693713",
  "客户 ${u.tenant_name}": "auto.e50d728c",
  "客户 · 接口 · 业务 关联关系": "auto.e8272417",
  "客户ID 如 SDWAN-BACKBONE": "auto.8df8734e",
  "客户ID:专线编码 如 SDWAN-BACKBONE:CIR-DD02B7": "auto.1f67f6c5",
  "客户·接口·业务 (${bindings?.total_bindings ?? 0})": "auto.8607d5c1",
  "客户名称": "auto.83b0d234",
  "客户已创建": "auto.143733fd",
  "客户服务 · 专线": "auto.0c25eea5",
  "客户门户账号 · ${tenantName}": "auto.91c31ccf",
  "容量数据加载失败，请稍后重试": "auto.c7b6e82c",
  "密码": "auto.a8105204",
  "密码 / 授权码": "auto.93b75d80",
  "密码为 Mailjet Secret Key。": "auto.304fbe0e",
  "密码为 Mandrill API Key。": "auto.21be4011",
  "密码已更新": "auto.fd5a3cf1",
  "密码已重置，请使用新密码登录": "auto.6c05949c",
  "对端": "auto.fa30c160",
  "对端 ASN": "auto.86fb42d2",
  "对端 IP": "auto.a446e556",
  "导入/新增设备后自动拉取": "auto.3c376f0e",
  "导入完成 · 新增 ${data.created} · 跳过 ${data.skipped}${learnMsg}": "auto.a0c36e14",
  "导出失败": "auto.dd51ab50",
  "封装": "auto.6912abd3",
  "封装模式": "auto.130711b5",
  "小图标 · 浏览器标签页": "auto.fd1fa546",
  "尚未执行现网学习": "auto.5f8f66e2",
  "尚未配置站点间链路": "auto.7a4d4d98",
  "展示设备全部已发现接口，含端口描述；评分高的排在前面": "auto.2780901d",
  "峰值利用率": "auto.d5d1b623",
  "峰值利用率告警 (%)": "auto.2809bd85",
  "峰值利用率阈值 (%)": "auto.0e9840b7",
  "巡检引擎待机": "auto.abe35e59",
  "巡检引擎运行中": "auto.484f6967",
  "工单": "auto.057efb37",
  "工单 ${current.code}": "auto.d395fa2f",
  "工单 ${data.code} 执行失败，请查看下发详情": "auto.21f08d86",
  "工单 ${wo.code} 执行失败，请查看下发详情": "auto.2be1e8f2",
  "工单号": "auto.769eb37b",
  "工单已撤销": "auto.dc88b7b2",
  "工单执行失败": "auto.25e26754",
  "工单执行完毕": "auto.e6591b4e",
  "工单状态轮询失败，请刷新页面查看进度": "auto.6d8f0f89",
  "已下载 Ansible inventory": "auto.f98e692f",
  "已下载 Ansible 压缩包（inventory + playbook + 设备配置）": "auto.a78380bc",
  "已从端口描述同步合同带宽": "auto.288dc779",
  "已保存 ${data.updated} 个接口描述（Dry-run：未真实下发）": "auto.f50e9b58",
  "已保存 ${data.updated} 个接口描述，但下发失败，请检查设备连通性": "auto.7228d41f",
  "已保存并下发 ${data.updated} 个接口描述": "auto.d1b8276a",
  "已关闭": "auto.9c58505d",
  "已分配 / 总容量": "auto.cf2f78db",
  "已分配带宽": "auto.923c5302",
  "已创建 ${picks.length} 条骨干链路": "auto.49720d4d",
  "已加入后台队列，正在等待工作线程执行…": "auto.662e8989",
  "已加入后台队列，等待执行…": "auto.995450d4",
  "已发现 ${data.length} 个接口，并更新 VLAN 占用": "auto.4c1a0a85",
  "已取消、草稿或未执行的工单不会出现在可选列表中。": "auto.e7b9fb89",
  "已启用": "auto.53ace430",
  "已启用 telemetry 模拟（BUGIS_TELEMETRY_SIMULATION）": "auto.c477a93d",
  "已回滚": "auto.ef6db9e1",
  "已扫描设备": "auto.62acdfcf",
  "已批准": "auto.337737f5",
  "已拆除": "auto.b96eda01",
  "已清除": "auto.59462c81",
  "已渲染": "auto.28a976e1",
  "已确认(自动)": "auto.c64506f4",
  "已自定义": "auto.73974967",
  "已设置，留空不修改": "auto.65d7bb45",
  "已设置，留空则不修改": "auto.c301423d",
  "已配置 · 留空不修改": "auto.eda003ac",
  "已验证发信域名地址": "auto.81abc912",
  "已验证的发件地址": "auto.e183ed2d",
  "带宽": "auto.0a21779c",
  "带宽 (Mbps)": "auto.8c245249",
  "带宽分配率": "auto.43718dd2",
  "平台": "auto.4981287f",
  "平台内置 · 自动注册": "auto.9d49ad12",
  "平台期望配置 (Desired)": "auto.3f7bf415",
  "平台纳管": "auto.baf8542a",
  "平台纳管 (${platformVnis.size})": "auto.02ee1f06",
  "平台设备": "auto.1c0e7562",
  "平台运行参数已保存": "auto.d16dd8e0",
  "平台默认": "auto.e5d59cce",
  "平台默认 ${platform.threshold_health_score} 分": "auto.d7dc0aa1",
  "平台默认 ${platform.threshold_latency_ms} ms": "auto.cfb75a72",
  "平台默认 ${platform.threshold_packet_loss_pct}%": "auto.3be19792",
  "平台默认 ${platform.threshold_utilization_pct}%": "auto.472a6a9b",
  "平均时延": "auto.470585dc",
  "并发下发数": "auto.8e3aade5",
  "延迟探测": "auto.add92603",
  "建议在生产环境启用 Turnstile 或前置 Cloudflare WAF，并为管理员开启 TOTP 验证器。": "auto.8f614a6e",
  "开启": "auto.cc42dd31",
  "开启后开通/拆除请求会进入后台队列(状态=排队中)立即返回，由工作线程异步下发，避免大量并发操作占满请求线程。前端在工单详情/进度弹窗中轮询进度。": "auto.200607fc",
  "开启后配置仅渲染预览、不推送到真实设备。": "auto.f04fd9ea",
  "开始": "auto.a3e3b883",
  "开始日期": "auto.b44c0f33",
  "开通": "auto.a06d405b",
  "开通/拆除前自动拉取各目标设备 running-config 存为 pre_change 快照，用于对比与应急还原": "auto.fd64d3fa",
  "开通下发": "auto.3c3938da",
  "开通失败": "auto.e544b00a",
  "异步开通（后台队列）": "auto.cd81342d",
  "强制平台账号 MFA": "auto.a1c3e247",
  "强制门户账号 MFA": "auto.e257fcf9",
  "强调色": "auto.b157dabe",
  "当前 ${total.toLocaleString()} 条专线${total > pageSize ? \" · 已分页\" : \"\"}": "auto.b378c581",
  "当前客户": "auto.5e560ed9",
  "当前密码": "auto.a806ce95",
  "当前按站点泳道展示纳管设备。在「容量规划」中添加 DCI / Fabric 链路后，拓扑图将自动绘制互联关系与带宽利用率。": "auto.35944b28",
  "当前登录密码": "auto.49e17ab3",
  "当前账号为只读权限，无法保存品牌设置": "auto.5a81171e",
  "待审批": "auto.b0bf01a4",
  "待执行": "auto.6139a699",
  "德国 DE": "auto.cb7447b6",
  "快捷": "auto.e5c2374e",
  "总计": "auto.599b5a32",
  "意图驱动，多厂商一键开通": "auto.1fc83255",
  "成功": "auto.330363df",
  "或管理 IP": "auto.65d5a9d4",
  "手动填写 SMTP 主机、端口与加密方式。": "auto.7553a06d",
  "手动备份": "auto.f20a1834",
  "手动选配": "auto.627d017c",
  "手工": "auto.bcf0046a",
  "托管专线开通后自动建立 BGP 对等": "auto.5bc66ee6",
  "执行失败，点击查看详情": "auto.4f887b54",
  "找回密码": "auto.ab978c6e",
  "抖动": "auto.f1b8e0c6",
  "抖动 (ms)": "auto.18b893d0",
  "拆除": "auto.ca698833",
  "拆除专线": "auto.51fdf294",
  "拆除回收": "auto.87a67f14",
  "拆除失败": "auto.0184755d",
  "拉取间隔 (秒)": "auto.2d52b76b",
  "拨测失败": "auto.3f60d8f1",
  "拨测结果 · ${data.circuit}": "auto.4a811a78",
  "按 VNI 过滤": "auto.2217be60",
  "按号码筛选 VNI 列表": "auto.724804c3",
  "按操作人筛选": "auto.ca86c386",
  "按设备反查 VNI": "auto.864f6f40",
  "排队中": "auto.e5ac1d20",
  "排除接口 (正则)": "auto.4dfdf15c",
  "探测": "auto.f6c10202",
  "探测失败": "auto.0dc2f390",
  "探测成功 · ${data.interfaces_found} 个接口": "auto.734605f9",
  "探测目标": "auto.bb287106",
  "接入": "auto.ca1fc273",
  "接入接口": "auto.7ceec493",
  "接入端点": "auto.b1d625d2",
  "接入绑定": "auto.33db5774",
  "接入设备": "auto.bb2ac125",
  "接口": "auto.54ea89b4",
  "接口 IP": "auto.7e3b29fa",
  "接口全名：${name}": "auto.df1e33b1",
  "控制台 SMTP 账号": "auto.14c6e3ee",
  "控制台发信地址": "auto.1b5da2ea",
  "控制器 BGP ASN": "auto.d5d050a0",
  "控制器北向下发": "auto.f0f26d5a",
  "控制器节点 ID": "auto.95605b8e",
  "控制器集群 · HA": "auto.6dc6f911",
  "描述": "auto.3bdd08ad",
  "搜狐邮箱": "auto.f00ab7cb",
  "搜狐邮箱地址": "auto.2137b7a1",
  "搜索专线编码或名称": "auto.637eab43",
  "搜索名称或管理 IP": "auto.49dc0efc",
  "搜索客户 / 接口 / 业务 / S-VID / 限速": "auto.da90df55",
  "搜索客户名称或编码": "auto.fe9ccb75",
  "搜索工单号 / 标题 / 申请人": "auto.130197ef",
  "搜索接口名 / 描述": "auto.ac5d314b",
  "搜索站点名称 / 编码": "auto.53a6db39",
  "搜索编码 / 名称": "auto.0c8402e7",
  "搜索链路 / 设备": "auto.f39abbaa",
  "撤销该工单？": "auto.326cebdf",
  "操作": "auto.2b6bc0f2",
  "操作人": "auto.f9ac4b2a",
  "操作日志 · 最近动态": "auto.f1518ddc",
  "支持主流邮件平台": "auto.7ac95736",
  "收件人邮箱": "auto.78dd8a0c",
  "收件人邮箱 noc@example.com": "auto.683c71ed",
  "收路由": "auto.fc76b075",
  "敏感字段不会回显": "auto.c5edfa1c",
  "数据中心": "auto.3c81db28",
  "数据库": "auto.68051bf4",
  "数据面编排绑定": "auto.ae3b3587",
  "新加坡": "auto.ce8a7b5b",
  "新加坡 SG": "auto.493c28c7",
  "新密码": "auto.bf7da0bf",
  "新密码至少 8 位": "auto.ac806d9b",
  "新建 Fabric 站点": "auto.f71517b1",
  "新建专线": "auto.10711205",
  "新建客户": "auto.82436793",
  "新建用户": "auto.92d61029",
  "新建通知渠道": "auto.684a8749",
  "新建门户账号": "auto.13793b33",
  "新浪邮箱": "auto.bf7f333b",
  "新浪邮箱地址": "auto.37297131",
  "方法": "auto.ea340b9d",
  "无 (Access 模式)": "auto.af0d2737",
  "无 SNMP 数据（请检查 SNMP 与接口 ifIndex）": "auto.395ba87c",
  "无加密 (端口 25，内网)": "auto.644fb890",
  "无匹配工单 · 调整筛选条件": "auto.c0300dcb",
  "无匹配站点": "auto.f78d205b",
  "无匹配链路": "auto.22f05c0c",
  "无占用 · 可分配": "auto.1cca0ae9",
  "无对端": "auto.e2b8a0cc",
  "无标签接入": "auto.c9190012",
  "无法打开该专线，可能不存在或无权查看": "auto.76b887fa",
  "无配置作业（可能被预检阻断）": "auto.744cedac",
  "日本 (东京)": "auto.35c2e90e",
  "日本 JP": "auto.2a4cb060",
  "时延": "auto.1f352317",
  "时延 (ms)": "auto.0c20c049",
  "时延 · 抖动 · 丢包（${windowLabel}）": "auto.9b7f474a",
  "时延/抖动": "auto.5c089d82",
  "时延告警 (ms)": "auto.f2e70ee6",
  "时延阈值 (ms)": "auto.d1b39fa4",
  "时长": "auto.5bdfd7ee",
  "时间": "auto.19fcb9eb",
  "显式 SR 路径": "auto.e928aef3",
  "显示名称": "auto.fdf6f7f6",
  "智能避让": "auto.91676e35",
  "暂停": "auto.8d63ef38",
  "暂无 S-VID 占用数据": "auto.4a835576",
  "暂无 S-VID 占用端口": "auto.d9d1ae06",
  "暂无 VTEP 邻居": "auto.9c93556d",
  "暂无专线，请联系运营商开通": "auto.8ad18a45",
  "暂无关联关系 · 请先现网学习并刷新占用": "auto.24e13f06",
  "暂无可导出工单": "auto.8a83de91",
  "暂无可监控专线": "auto.54c115f7",
  "暂无可监控的运行中专线": "auto.98a1c613",
  "暂无快照，点击「备份现网配置」": "auto.f4a2ab36",
  "暂无拨测数据 · 调度器轮询或手动「端到端拨测」后显示": "auto.bf677836",
  "暂无推荐 · 请确认设备已 SNMP 发现且跨站点存在未建链路": "auto.3a2205c8",
  "暂无数据面绑定记录": "auto.0b1115f1",
  "暂无现网 Overlay 数据 · 请对设备执行现网学习后扫描": "auto.6fe32c93",
  "暂无现网学习快照": "auto.299441a6",
  "暂无站点 · 点击右上角新建": "auto.5cacb65d",
  "暂无站点容量数据": "auto.1671b025",
  "暂无端口数据 · 将自动尝试 SNMP 发现": "auto.59408419",
  "暂无纳管设备 · 先在「网络设备」中添加": "auto.b5336188",
  "暂无门户账号": "auto.8b6d5de3",
  "暂无骨干链路 · 点击「配置骨干链路」智能推荐或手动选配": "auto.5087451f",
  "暴露 OpenAPI 文档 (/docs)": "auto.dcf5b7b6",
  "更新失败": "auto.930442e2",
  "最近发送": "auto.2c6aa24c",
  "最近心跳": "auto.9a36d2f3",
  "最近拉取": "auto.d261f97b",
  "最近结果": "auto.0fb9614a",
  "最近设备数": "auto.463107ec",
  "最长 63 字符": "auto.46acd24f",
  "未分配站点": "auto.da50c2e6",
  "未发现 Vlanif / Vlan-interface，请在设备页执行 SNMP 发现或现网学习后刷新": "auto.6e5082b0",
  "未找到客户": "auto.bef06baa",
  "未找到该专线或无访问权限": "auto.e987c729",
  "未纳管": "auto.d302a763",
  "未解析到 S-VID，请确认设备 running-config 含 service-instance / dot1q 配置": "auto.d06999ca",
  "未配置": "auto.71dc8feb",
  "本地 ASN": "auto.780e33f1",
  "本年": "auto.04ab9d43",
  "本月": "auto.0ec94a37",
  "本机": "auto.4d1636e4",
  "条": "auto.cc1bacb5",
  "来源": "auto.26ca20b1",
  "来源 IP": "auto.11c50da4",
  "来源: ${src}": "auto.2674aae8",
  "标签": "auto.14d34236",
  "标题": "auto.32c65d8d",
  "检测": "auto.69d60050",
  "检测时自动发现": "auto.6dec192c",
  "模式": "auto.f0789e79",
  "模拟": "auto.dc723a61",
  "模拟估算": "auto.62469bc0",
  "模拟成功": "auto.9c189be9",
  "横幅主标题": "auto.30ed0e23",
  "横幅副标题": "auto.62a20119",
  "正在创建工单并推送配置…": "auto.0c49f6c4",
  "正在向各端设备下发配置…": "auto.1ee0e682",
  "正在向各端设备渲染并下发配置，请稍候…": "auto.9d06ca8c",
  "正在回收各端设备配置…": "auto.19946c0f",
  "正在回收各端设备配置并释放资源，请稍候…": "auto.a3d27fff",
  "正在拉取设备 running-config...": "auto.4e0ca394",
  "正在拨测 ${c.code} ...": "auto.38016bcc",
  "此操作不可撤销，将永久删除该设备及其关联数据。": "auto.b62871c2",
  "段 RTT(ms)": "auto.c97fe6a3",
  "每一行表示一个 S-VID 绑定：客户是谁、落在哪个物理口、承载哪条业务，以及端口限速带宽。": "auto.c6fb0261",
  "永久删除记录": "auto.14285de5",
  "没有需要保存的描述变更": "auto.98785e02",
  "活跃专线": "auto.de04e9ea",
  "活跃告警": "auto.683a67da",
  "活跃带宽": "auto.aabe3bbc",
  "流量 ${fmtBw(r.traffic_mbps)} · 峰值 ${r.peak_utilization_pct ?? v}% · 告警阈值 ${r.effective_alarm_utilization_pct ?? \"—\"}%": "auto.829cc7d2",
  "流量 / 95 / 监控": "auto.c500e18a",
  "流量 · Rx / Tx（${windowLabel}，${chartData.length} 点）": "auto.de61ee42",
  "流量 · 带宽 · 95 计费": "auto.5f3bfbd2",
  "流量监控": "auto.666eb475",
  "测试通知已发送": "auto.1e710e30",
  "涵盖 QQ / 163 / 企业邮、Gmail / Outlook、SendGrid / Mailgun / AWS SES 等，选择后自动填入 SMTP 主机、端口与加密方式，仅需填写账号与授权码。": "auto.bc7977e0",
  "混合云接入": "auto.b42d982f",
  "添加/登记端点 · ${editEndpointsTarget.code}": "auto.d1801335",
  "添加端点（不下发）": "auto.bc9c7b1e",
  "渲染配置片段": "auto.6496d812",
  "漂移行数": "auto.1295ec23",
  "澳大利亚 AU": "auto.de312ac4",
  "版本": "auto.fe2df04a",
  "版本历史 (${snaps.length})": "auto.3c7baf16",
  "物理口来自 running-config 解析": "auto.8e256a66",
  "物理端口": "auto.1bae47f4",
  "物理端口 (${physicalPorts.length})": "auto.97a72238",
  "状态": "auto.3fea7ca7",
  "状态 ${online ? \"在线\" : n.status}": "auto.2cb07415",
  "状态码": "auto.771d897d",
  "状态筛选": "auto.02c92bca",
  "环境": "auto.fa405f59",
  "现网 VNI / VSI 占用扫描": "auto.19582ddb",
  "现网保留 VNI": "auto.243089db",
  "现网占用": "auto.2d6c9a14",
  "现网学习": "auto.04002781",
  "现网扫描完成 · ${data.network_only_services ?? 0} 个未纳管服务 · 保留 ${data.reserved_vni_count ?? 0} 个 VNI": "auto.82706256",
  "现网拉取": "auto.e287365b",
  "现网未纳管": "auto.852848ce",
  "现网纳管（不下发配置）": "auto.75058456",
  "现网配置保护": "auto.573cea55",
  "现网配置学习中 · ${d.name}...": "auto.e345c343",
  "现网配置学习中...": "auto.cb3bb6f2",
  "现网配置学习完成": "auto.09dad583",
  "现网配置自动拉取": "auto.4aed0b45",
  "生产数据采集模式：指标来自 SNMP 与南向拨测": "auto.b8015180",
  "生产模式（真实下发）": "auto.8d55ca11",
  "用户名": "auto.819767ad",
  "用户名 / 账号": "auto.62a1d8ff",
  "用户名固定为 apikey，密码为 SendGrid API Key。": "auto.74d16d91",
  "申请人": "auto.8ac8da83",
  "留空不修改": "auto.ed75a01c",
  "留空使用平台默认": "auto.ca8ad0f2",
  "留空使用平台默认 ${platform.threshold_link_utilization_pct}%": "auto.5cc867f5",
  "留空保持原值": "auto.81c7c3fa",
  "留空则不修改；如需重置请输入至少 8 位新密码": "auto.3b74ff3d",
  "留空则平台自动分配，不可与已有专线重复": "auto.a9a2f4f6",
  "留空则按厂商自动选择": "auto.25f78070",
  "留空则按厂商自动选择，如 hp_comware、cisco_xr": "auto.81cb6426",
  "登录 Token 有效期 (分钟)": "auto.8ebf0e78",
  "登录以进入 ${brand.product_name}": "auto.c0b8abbc",
  "登录副标题": "auto.caa88187",
  "登录密码": "auto.2646b813",
  "登录密码、Enable 密码与 SNMP 密钥留空则不修改。厂商纳管后不可变更。": "auto.c61ed7e2",
  "登录标题": "auto.43d1630b",
  "登录用户名": "auto.39b5f451",
  "登录邮箱": "auto.8f0aa201",
  "登录页背景": "auto.8209cc0c",
  "直连下发 (NETCONF/CLI)": "auto.1af0f374",
  "确定": "auto.38cf16f2",
  "确认删除?": "auto.fc98faab",
  "确认删除用户 ${row.username}？此操作不可恢复。": "auto.debdeb32",
  "确认删除该站点?": "auto.2cbd84ab",
  "确认删除该设备?": "auto.82644821",
  "确认失败": "auto.c92aaa37",
  "确认拆除该专线?": "auto.c47a29a1",
  "确认新密码": "auto.670d631e",
  "确认永久删除该专线记录?": "auto.d3f40cb3",
  "禁用": "auto.710ad08b",
  "种": "auto.b13903ce",
  "窗口 95 计费": "auto.3262a08b",
  "站内互联": "auto.a46e14c6",
  "站点": "auto.236ed6c0",
  "站点名称": "auto.70889e0b",
  "端到端拨测": "auto.c47773b0",
  "端口": "auto.c76cfefe",
  "端口清单": "auto.d6e601b7",
  "端口清单 · ${device.name}": "auto.28325ca3",
  "端点": "auto.cf28e8ea",
  "端点 ${ep.label}": "auto.e0f5ec79",
  "端点已登记 · ${data.endpoints?.length ?? endpoints.length} 个节点（未向设备下发配置）": "auto.8b5ef4db",
  "端点更新失败": "auto.7733ce07",
  "第 ${range[0].toLocaleString()}–${range[1].toLocaleString()} 条，共 ${t.toLocaleString()} 条": "auto.a0708009",
  "第 ${start.toLocaleString()}–${end.toLocaleString()} 条，共 ${total.toLocaleString()} 条": "auto.37154f85",
  "等待结果": "auto.1d6d55b9",
  "筛选出 ${filtered.length} / ${rows.length} 条": "auto.90381bae",
  "筛选客户（搜索名称或编码）": "auto.136bf8f3",
  "签约带宽": "auto.f06fa8be",
  "管理 IP": "auto.8659ea73",
  "管理员": "auto.b1dae9bc",
  "管理员 — 可管理门户账号": "auto.103d76e0",
  "管理网": "auto.45010a67",
  "类型": "auto.226b0912",
  "系统按采样点聚合流量，取所选时间窗口内第 95 百分位作为计费带宽（入向/出向取较大值）。切换快捷时间范围会自动刷新图表；自选时间需点击「查询」。": "auto.0136f379",
  "索引": "auto.b271e427",
  "累计 RTT(ms)": "auto.ec3ecb64",
  "级别": "auto.e78e4b2d",
  "纳管专线 · 登记接入端点": "auto.e9ab3d2a",
  "纳管到平台": "auto.fc1df8e6",
  "纳管后不可修改": "auto.d4bbd4da",
  "纳管外部控制器": "auto.8c721827",
  "纳管失败": "auto.96ef319c",
  "纳管成功，已登记到平台（未下发配置）": "auto.ac3c8528",
  "纳管现网业务": "auto.311f04ab",
  "纳管设备": "auto.76acdc7f",
  "组织需允许 SMTP AUTH；部分租户需开启基本身份验证例外。": "auto.3da8f9df",
  "结束": "auto.12f1d7ef",
  "结束日期": "auto.1d468be9",
  "结果确认": "auto.94070693",
  "统计窗口 (分钟)": "auto.b0400870",
  "继续开通": "auto.5e16ec4d",
  "编排下发": "auto.d534eac8",
  "编码": "auto.cc6c35a3",
  "编辑工单": "auto.cca7012c",
  "编辑用户": "auto.5a0346c4",
  "编辑端点与告警阈值": "auto.d853c277",
  "编辑设备 · ${device.name}": "auto.df962dbf",
  "编辑设备信息": "auto.45e86afc",
  "编辑骨干链路": "auto.7b84f3a3",
  "网关": "auto.f332f2c8",
  "网易 126": "auto.beda2438",
  "网易 163": "auto.843f89f9",
  "网易 Yeah.net": "auto.0b158024",
  "网易企业邮": "auto.33caceb4",
  "美国 US": "auto.f12914d6",
  "美国东部": "auto.3e8befb0",
  "美国中部": "auto.a5192b1d",
  "美国太平洋": "auto.81ec5af9",
  "联系人": "auto.52409da5",
  "腾讯云 SES 控制台 → 发信地址 → SMTP 设置。": "auto.a9cab462",
  "腾讯云邮件推送": "auto.a4ab5cdc",
  "腾讯企业邮": "auto.80d43d86",
  "腾讯企业邮 / 微信企业邮箱管理后台可查看 SMTP 参数。": "auto.631ae2e8",
  "自动 (IS-IS SR 最短路径)": "auto.a0a755cf",
  "自动分配": "auto.4fb763c2",
  "自动生成": "auto.cc217739",
  "自定义 / 其他": "auto.23afbc31",
  "自选": "auto.aa3a809e",
  "至少 8 位": "auto.3788acb9",
  "至少需要 ${minEps} 个端点": "auto.2cfda319",
  "节点": "auto.3bf3c0a8",
  "若账号存在，验证码已发送至邮箱": "auto.7abf3f93",
  "英国 (伦敦)": "auto.bd62904e",
  "英国 GB": "auto.c1c2fe21",
  "行为": "auto.a0496123",
  "行数": "auto.65680044",
  "表单数据加载失败，请刷新页面后重试": "auto.c43cafea",
  "触发阈值": "auto.e6f34570",
  "触发阈值 (达到该级别及以上发送)": "auto.925e7814",
  "计费 95": "auto.a31a7960",
  "认证密码": "auto.d95becc2",
  "认证算法": "auto.6a4cc82a",
  "设备": "auto.f55f1736",
  "设备 #${j.device_id}": "auto.0f330c77",
  "设备 ID": "auto.90793765",
  "设备 · 在线/总量": "auto.fd662dbe",
  "设备作业 ${okJobs}/${jobs.length}": "auto.0e4e5abe",
  "设备列表加载失败": "auto.87cc077e",
  "设备厂商 · 异构分布": "auto.e728e425",
  "设备基线参数已保存": "auto.5e379cf0",
  "设备已纳管": "auto.784ee62a",
  "设备总数": "auto.c615660d",
  "设备数": "auto.ca55443a",
  "设备配置": "auto.fe0e473e",
  "设备配置加载失败": "auto.29062126",
  "评估完成 · ${data.evaluated} 条专线 · 活跃告警 ${data.active_alarms}": "auto.6411bb43",
  "评分": "auto.108db12e",
  "该工单无可导出配置（已取消/未执行的工单无法导出）": "auto.3181c9f3",
  "该工单无可导出配置，请选择已完成的开通/变更工单": "auto.c4392671",
  "该端口已有 VLAN 封装，无法再配置 untagged": "auto.7d5cf9ee",
  "该端口已配置 untagged 接入": "auto.5cd4876b",
  "该端口已配置 untagged，无法叠加 VLAN": "auto.d5510c8b",
  "该端口暂无 VLAN 占用": "auto.cbf1ec0c",
  "详情": "auto.f26225bd",
  "说明": "auto.f411d0f1",
  "请使用验证器 App 扫描二维码或手动输入密钥": "auto.9cc10954",
  "请先在「专线开通」完成一条专线的开通工单（状态 completed），再回来导出。": "auto.c76aaef2",
  "请先完成人机验证": "auto.22cb3d0c",
  "请先执行「现网学习」拉取 running-config，再点「检测 S-VID」或「刷新占用」。": "auto.1b362248",
  "请先选择至少两个端点设备": "auto.f6ffeada",
  "请先选择设备": "auto.7b0db2a0",
  "请再次输入新密码": "auto.d98a14a9",
  "请填写拉取间隔": "auto.917b2f45",
  "请查看下方设备作业与流转轨迹中的错误信息": "auto.d996fc58",
  "请至少选择一条推荐链路": "auto.159fd267",
  "请输入 6 位验证码": "auto.558bd4be",
  "请输入 SMTP 主机": "auto.b1ec0548",
  "请输入主管理 IP": "auto.235b5e4e",
  "请输入双因素验证码": "auto.567032bb",
  "请输入名称": "auto.06e2f88f",
  "请输入密码": "auto.e39ffe99",
  "请输入密码与验证码": "auto.c1d62bcb",
  "请输入当前密码": "auto.cd043c16",
  "请输入新密码": "auto.abdd7ea8",
  "请输入用户名": "auto.08b1fa13",
  "请输入用户名和密码": "auto.dab2bcf0",
  "请输入用户名或绑定邮箱": "auto.11e22032",
  "请输入用户名或邮箱": "auto.0db6723c",
  "请输入登录密码与验证码": "auto.064c9f86",
  "请输入设备名称": "auto.dd73090a",
  "请输入验证器或邮件中的 6 位验证码以完成登录": "auto.cd695c7e",
  "请输入验证码": "auto.d0c06a0d",
  "请选择": "auto.708c9d6d",
  "请选择 A 端设备": "auto.aecfad99",
  "请选择 Z 端设备": "auto.9c87e7b2",
  "请选择出口国家": "auto.c4bccea6",
  "请选择出口站点": "auto.33687e00",
  "请选择客户": "auto.185c0503",
  "请选择工单": "auto.3e86d8ca",
  "请选择端口": "auto.b3d4f896",
  "请选择设备": "auto.3e3fb228",
  "请选择起始与终止时间后点击「查询」": "auto.3611d339",
  "读写 Community (可选)": "auto.2d108f58",
  "调度器": "auto.ee02035d",
  "调度间隔 (秒)": "auto.7e8623a5",
  "账号锁定阈值": "auto.710c1ec4",
  "资源已释放，拆除完成": "auto.db8bad5d",
  "资源释放": "auto.0db187a0",
  "超时 (秒)": "auto.52e9bc2c",
  "跨 DC / 跨域互联": "auto.8bd23a0e",
  "跨站点 DCI": "auto.07926185",
  "路径": "auto.4f35e80d",
  "路由反射器": "auto.ca6ba0c9",
  "跳": "auto.f4965ce1",
  "输入或选择 VNI": "auto.7e1b8962",
  "输入账号用户名或绑定邮箱，我们将发送验证码到邮箱": "auto.8c973328",
  "输入邮箱收到的验证码并设置新的登录密码": "auto.71b30229",
  "迁移": "auto.26defddb",
  "近 ${hours}h": "auto.88e746ec",
  "返回的是模拟数据（设备 SNMP 不可达或 Community/端口错误）。华为请确认 UDP 16161 与管理网 IP 可达后重试": "auto.36941da1",
  "进行中": "auto.fb852fc6",
  "远程登录凭证说明": "auto.4496c2fb",
  "选择 VTEP / PE / Leaf": "auto.c0fe1b92",
  "选择专线": "auto.3b87cc38",
  "选择右侧 VNI 查看隧道互联": "auto.7980cd12",
  "选择左侧设备": "auto.8bc74129",
  "选择已完成的工单": "auto.1ca40245",
  "选择接口": "auto.d84b8d7f",
  "选择站点": "auto.a75ab7cd",
  "选择端口（下拉可查看占用详情）": "auto.70624131",
  "选择经由设备": "auto.be7dad83",
  "选择设备": "auto.15d00b96",
  "选择邮件服务商": "auto.da27a16d",
  "选用 Vlan-interface / Vlanif 子接口；端口描述标注 bw(100Mbps) 可自动写入合同带宽；利用率超链路或平台阈值触发告警": "auto.8aaa1f57",
  "选路模式": "auto.bec24f6d",
  "通用 Webhook": "auto.9bb27195",
  "速率": "auto.a63db188",
  "邮件 (SMTP)": "auto.3258ca5b",
  "邮件发送失败": "auto.c2c942b3",
  "邮件平台": "auto.c8c6fd4b",
  "部分接口为模拟数据（${simCount}/${data.length}），请检查 SNMP 配置": "auto.2e7eb820",
  "部分数据加载失败: ${failed.join(\", \")}，请刷新页面重试": "auto.2a62df9b",
  "部分端口为模拟数据": "auto.0e4b5738",
  "配置下发传输": "auto.04e76cc8",
  "配置作业": "auto.2104ba7d",
  "配置历史 · ${historyCircuit?.code || \"\"}": "auto.11e4eede",
  "配置历史与对比": "auto.af7ef319",
  "配置回收": "auto.da9062e4",
  "配置将通过 NETCONF/SSH 真实下发到设备，请确认设备凭证与网络可达性。": "auto.603f75f4",
  "配置已下发完成": "auto.b41c8201",
  "配置已回收完成": "auto.3629bb6d",
  "配置快照 v${data.version}": "auto.f12476f3",
  "配置版本化": "auto.0286f195",
  "配置管理参数已保存": "auto.233eab07",
  "配置预览 · ${c.code} (${c.name})": "auto.051687a8",
  "配置预览失败": "auto.8f95746b",
  "配置骨干链路": "auto.db54dafa",
  "采集范围": "auto.3d4e8a09",
  "重新下发": "auto.572dba08",
  "重新下发配置 (re-apply)": "auto.f0e95ccc",
  "重置失败，请检查验证码": "auto.2992d67b",
  "重置密码": "auto.0719aa2b",
  "重置密码并返回登录": "auto.c7c72a5b",
  "重试": "auto.132c5cdc",
  "钉钉": "auto.4a0e9142",
  "链路": "auto.70bd0d7f",
  "链路利用率阈值 (%)": "auto.03b4a1bd",
  "链路名称": "auto.49ebea57",
  "链路负载 · DCI / Fabric": "auto.7628f561",
  "链路配置": "auto.4c95b8df",
  "锁定时长 (分钟)": "auto.76c9a1db",
  "门户账号已创建": "auto.41fdeaea",
  "闪断": "auto.a24e4994",
  "阿联酋 (迪拜)": "auto.cb38d538",
  "阿里个人邮箱": "auto.3d36d7c2",
  "阿里云 DirectMail 控制台获取 SMTP 账号与密码。": "auto.d5030168",
  "阿里云企业邮箱（万网邮）SMTP 服务器。": "auto.b2f37728",
  "阿里云邮件推送": "auto.8db7d036",
  "阿里企业邮": "auto.33df5537",
  "阿里邮箱地址": "auto.e038298d",
  "限速 ${u.rate_limit_mbps}M": "auto.0a4fac86",
  "限速带宽": "auto.c8420c24",
  "隧道": "auto.f515fce4",
  "集成中心": "auto.d91cba85",
  "集群模式": "auto.6955953a",
  "需使用应用密码。": "auto.d73910a7",
  "需在 QQ 邮箱设置中开启 SMTP 并使用授权码（非 QQ 密码）。": "auto.d2c50691",
  "需在本机运行 Proton Mail Bridge。": "auto.92cfd632",
  "需在网易邮箱 → 设置 → POP3/SMTP 中开启并获取授权码。": "auto.c267e2c8",
  "需在飞书管理后台开启第三方客户端 / SMTP。": "auto.7c45444e",
  "需开启 SMTP 并使用客户端授权码。": "auto.74cc17f1",
  "需开启 SMTP 并使用授权码。": "auto.79ed08f5",
  "需开启两步验证并使用应用专用密码（App Password）。": "auto.c1acdf2f",
  "需生成应用专用密码。": "auto.2212f921",
  "需要完成人机验证后重试": "auto.a39cd568",
  "非完整生产数据模式": "auto.310a5f17",
  "非激活 · 模拟": "auto.1831706c",
  "韩国 (首尔)": "auto.661f6abc",
  "韩国 KR": "auto.a0ccf78d",
  "顶栏标题": "auto.84e05510",
  "预检发现 ${v.errors} 个错误": "auto.d3429490",
  "预检发现 ${v.warnings} 个告警": "auto.1ccec2d7",
  "预览各厂商配置": "auto.77da307e",
  "预览失败": "auto.6a3a5ef0",
  "飞书 / Lark": "auto.29e87066",
  "飞书企业邮箱": "auto.143a07c3",
  "飞书邮箱账号": "auto.ba9e9b79",
  "香港 HK": "auto.07ad67b5",
  "验证器 MFA 已启用": "auto.12eec3a5",
  "验证并登录": "auto.d042427d",
  "验证码": "auto.983f59c9",
  "验证码已发送至邮箱": "auto.fe3ceb7d",
  "验证码错误": "auto.08e91fbb",
  "骨干链路 · 利用率（${links.length}）": "auto.c7bb280f",
  "骨干链路已创建": "auto.251814da",
  "骨干链路已删除": "auto.5cc970db",
  "骨干链路已更新": "auto.850c371e",
  "高级参数（留空则使用平台默认）": "auto.03d46af0",
  "默认 NETCONF 830 / SSH 22；账号常为 admin 或 netconf": "auto.50f89776",
  "默认 NETCONF 830；账号常为 netconf": "auto.aad6e711",
  "默认 NETCONF 830；账号常为 netconf 或 huawei": "auto.cf7aa448",
  "默认 NETCONF 端口": "auto.07e8eefd",
  "默认 SSH 端口": "auto.626a3be8",
  "默认 SSH/eAPI；部分场景用 admin": "auto.e99555ee",
  "默认用户名": "auto.7f5b5ca0",
  "（主备自动切换）": "auto.00886046"
}